peakrdl_format_trans/__about__.py
peakrdl_format_trans/__init__.py
peakrdl_format_trans/__peakrdl__.py
peakrdl_format_trans/exporter.py
peakrdl_format_trans/format_translator.py
peakrdl_format_trans/importer.py
peakrdl_format_trans/rkvGensystemRDL.py
peakrdl_format_trans-3.6.0.dist-info/LICENSE
peakrdl_format_trans-3.6.0.dist-info/METADATA
peakrdl_format_trans-3.6.0.dist-info/WHEEL
peakrdl_format_trans-3.6.0.dist-info/entry_points.txt
peakrdl_format_trans-3.6.0.dist-info/top_level.txt
peakrdl_format_trans-3.6.0.dist-info/RECORD
