Metadata-Version: 2.1
Name: peakrdl-format-trans
Version: 3.6.0
Summary: # format_trans
Home-page: https://github.com/jiangqingliu88/peakrdl_format_trans
Author: jiangqingliu
Author-email: jiangqingliu822@gmail.com
License: LICENSE
License-File: LICENSE
